dojo_ftp/__init__.py
dojo_ftp/source.py
dojo_ftp-0.0.2.dist-info/DESCRIPTION.rst
dojo_ftp-0.0.2.dist-info/METADATA
dojo_ftp-0.0.2.dist-info/RECORD
dojo_ftp-0.0.2.dist-info/WHEEL
dojo_ftp-0.0.2.dist-info/metadata.json
dojo_ftp-0.0.2.dist-info/top_level.txt
